llama_toolchain/__init__.py
llama_toolchain/apis/__init__.py
llama_toolchain/apis/agents/__init__.py
llama_toolchain/apis/agents/agents.py
llama_toolchain/apis/agents/client.py
llama_toolchain/apis/agents/event_logger.py
llama_toolchain/apis/batch_inference/__init__.py
llama_toolchain/apis/batch_inference/batch_inference.py
llama_toolchain/apis/common/__init__.py
llama_toolchain/apis/common/deployment_types.py
llama_toolchain/apis/common/training_types.py
llama_toolchain/apis/dataset/__init__.py
llama_toolchain/apis/dataset/dataset.py
llama_toolchain/apis/evals/__init__.py
llama_toolchain/apis/evals/evals.py
llama_toolchain/apis/inference/__init__.py
llama_toolchain/apis/inference/client.py
llama_toolchain/apis/inference/event_logger.py
llama_toolchain/apis/inference/inference.py
llama_toolchain/apis/memory/__init__.py
llama_toolchain/apis/memory/client.py
llama_toolchain/apis/memory/memory.py
llama_toolchain/apis/memory_banks/__init__.py
llama_toolchain/apis/memory_banks/client.py
llama_toolchain/apis/memory_banks/memory_banks.py
llama_toolchain/apis/models/__init__.py
llama_toolchain/apis/models/client.py
llama_toolchain/apis/models/models.py
llama_toolchain/apis/post_training/__init__.py
llama_toolchain/apis/post_training/post_training.py
llama_toolchain/apis/reward_scoring/__init__.py
llama_toolchain/apis/reward_scoring/reward_scoring.py
llama_toolchain/apis/safety/__init__.py
llama_toolchain/apis/safety/client.py
llama_toolchain/apis/safety/safety.py
llama_toolchain/apis/shields/__init__.py
llama_toolchain/apis/shields/client.py
llama_toolchain/apis/shields/shields.py
llama_toolchain/apis/synthetic_data_generation/__init__.py
llama_toolchain/apis/synthetic_data_generation/synthetic_data_generation.py
llama_toolchain/apis/telemetry/__init__.py
llama_toolchain/apis/telemetry/telemetry.py
llama_toolchain/cli/__init__.py
llama_toolchain/cli/download.py
llama_toolchain/cli/llama.py
llama_toolchain/cli/subcommand.py
llama_toolchain/cli/table.py
llama_toolchain-0.0.35.dist-info/LICENSE
llama_toolchain-0.0.35.dist-info/METADATA
llama_toolchain-0.0.35.dist-info/WHEEL
llama_toolchain-0.0.35.dist-info/entry_points.txt
llama_toolchain-0.0.35.dist-info/top_level.txt
llama_toolchain-0.0.35.dist-info/RECORD
