Metadata-Version: 2.1
Name: llama_toolchain
Version: 0.0.35
Summary: Llama Stack
Home-page: https://github.com/meta-llama/llama-stack
Author: Meta Llama
Author-email: llama-oss@meta.com
Requires-Python: >=3.10
License-File: LICENSE
Requires-Dist: blobfile
Requires-Dist: fire
Requires-Dist: httpx
Requires-Dist: huggingface-hub
Requires-Dist: llama-models >=0.0.35
Requires-Dist: prompt-toolkit
Requires-Dist: python-dotenv
Requires-Dist: pydantic
Requires-Dist: requests
Requires-Dist: rich
Requires-Dist: termcolor
